voicemcpserver/__init__.py
voicemcpserver/server.py
voicemcpserver/voices.py
voicemcpserver-0.2.0.dist-info/METADATA
voicemcpserver-0.2.0.dist-info/WHEEL
voicemcpserver-0.2.0.dist-info/entry_points.txt
voicemcpserver-0.2.0.dist-info/RECORD
