Metadata-Version: 2.4
Name: voicemcpserver
Version: 0.2.0
Summary: MCP Server for Alibaba Cloud CosyVoice
Requires-Python: >=3.10
Requires-Dist: dashscope>=1.14.0
Requires-Dist: mcp>=0.1.0
Requires-Dist: python-dotenv>=1.0.0
